LICENSE
MANIFEST.in
README.md
new-theme.py
setup.py
flask_theme/__init__.py
flask_theme.egg-info/PKG-INFO
flask_theme.egg-info/SOURCES.txt
flask_theme.egg-info/dependency_links.txt
flask_theme.egg-info/not-zip-safe
flask_theme.egg-info/requires.txt
flask_theme.egg-info/top_level.txt
tests/test-themes.py
tests/morethemes/cool/info.json
tests/morethemes/cool/templates/active.html
tests/morethemes/cool/templates/static.html
tests/morethemes/cool/templates/你好.html
tests/templates/active.html
tests/templates/hello.html
tests/templates/static.html
tests/templates/static_parent.html
tests/themes/cool/info.json
tests/themes/cool/templates/hello.html
tests/themes/identifier/info.json
tests/themes/notthis/info.json
tests/themes/plain/info.json
tests/themes/plain/license.txt
tests/themes/plain/templates/static.html
tests/themes/warm-theme/info.json